{"id":"ep4j9qx8bktxsxsfvxyb32x","title":"Custom Styling","desc":"","updated":1701875612159,"created":1701875273319,"custom":{},"fname":"programming.side projects.flavor flash journal.style guide.custom styling","type":"note","vault":{"fsPath":".","selfContained":true,"name":"Dendron"},"contentHash":"a176f64573affd5de542a2f2594dded2","links":[],"anchors":{"buttonstyle-togglestyle-etc":{"type":"header","text":"ButtonStyle, ToggleStyle, etc","value":"buttonstyle-togglestyle-etc","line":8,"column":0,"depth":2}},"children":[],"parent":"snyjwumcbhskqfobufygzto","data":{}}
