{"id":"m30ay8bv1fkxsl30m2r9frl","title":"Enumeration","desc":"","updated":1704208895807,"created":1703951656006,"custom":{},"fname":"programming.language.swift.Types.enumeration","type":"note","vault":{"fsPath":".","selfContained":true,"name":"Dendron"},"contentHash":"1e14efc26b80b786855c9363afe4ea5b","links":[],"anchors":{"what-is-enum":{"type":"header","text":"What is enum?","value":"what-is-enum","line":8,"column":0,"depth":2},"declaration":{"type":"header","text":"Declaration","value":"declaration","line":12,"column":0,"depth":2},"用enum的優勢":{"type":"header","text":"用enum的優勢","value":"用enum的優勢","line":23,"column":0,"depth":2},"use-cases":{"type":"header","text":"Use Cases","value":"use-cases","line":52,"column":0,"depth":2}},"children":[],"parent":"mr2culexmtziuklrq2gt22f","data":{}}
